tracksdata/__about__.py
tracksdata/__init__.py
tracksdata/attrs.py
tracksdata/conftest.py
tracksdata/constants.py
tracksdata/options.py
tracksdata/_test/test_attrs.py
tracksdata/_test/test_options.py
tracksdata/array/__init__.py
tracksdata/array/_base_array.py
tracksdata/array/_graph_array.py
tracksdata/array/_nd_chunk_cache.py
tracksdata/array/_test/test_graph_array.py
tracksdata/array/_test/test_nd_chunk_cache.py
tracksdata/edges/__init__.py
tracksdata/edges/_base_edge_attrs.py
tracksdata/edges/_base_edges.py
tracksdata/edges/_distance_edges.py
tracksdata/edges/_generic_edges.py
tracksdata/edges/_iou_edges.py
tracksdata/edges/_test/test_distance_edges.py
tracksdata/edges/_test/test_generic_edges.py
tracksdata/edges/_test/test_iou_edges.py
tracksdata/functional/__init__.py
tracksdata/functional/_edges.py
tracksdata/functional/_iou.py
tracksdata/functional/_napari.py
tracksdata/functional/_rx.py
tracksdata/functional/_test/test_functional_edges.py
tracksdata/functional/_test/test_iou.py
tracksdata/functional/_test/test_napari.py
tracksdata/functional/_test/test_rx.py
tracksdata/graph/__init__.py
tracksdata/graph/_base_graph.py
tracksdata/graph/_graph_view.py
tracksdata/graph/_mapped_graph_mixin.py
tracksdata/graph/_rustworkx_graph.py
tracksdata/graph/_sql_graph.py
tracksdata/graph/_test/test_graph_backends.py
tracksdata/graph/_test/test_index_graph.py
tracksdata/graph/_test/test_subgraph.py
tracksdata/graph/filters/__init__.py
tracksdata/graph/filters/_base_filter.py
tracksdata/graph/filters/_indexed_filter.py
tracksdata/graph/filters/_spatial_filter.py
tracksdata/graph/filters/_test/test_spatial_filter.py
tracksdata/io/__init__.py
tracksdata/io/_ctc.py
tracksdata/io/_numpy_array.py
tracksdata/io/_test/test_ctc_io.py
tracksdata/metrics/__init__.py
tracksdata/metrics/_ctc_metrics.py
tracksdata/metrics/_visualize.py
tracksdata/metrics/_test/test_ctc_metrics.py
tracksdata/metrics/_test/test_metrics_visualize.py
tracksdata/nodes/__init__.py
tracksdata-0.1.0rc0.dist-info/METADATA
tracksdata-0.1.0rc0.dist-info/WHEEL
tracksdata-0.1.0rc0.dist-info/licenses/LICENSE
tracksdata-0.1.0rc0.dist-info/RECORD
